jafdecs/__init__.py
jafdecs/initialize.py
jafdecs/utilities.py
jafdecs/worm.py
jafdecs-0.1.0a2.dist-info/METADATA
jafdecs-0.1.0a2.dist-info/WHEEL
jafdecs-0.1.0a2.dist-info/top_level.txt
jafdecs-0.1.0a2.dist-info/RECORD
