Metadata-Version: 2.1
Name: jafdecs
Version: 0.1.0a2
Summary: A few useful decorators for Python functions, classes, class methods, and properties.
Author: Doug McGeehan
Author-email: doug@kmnr.org
License: GPLv3
Keywords: decorators,caching,write once read many
Classifier: Programming Language :: Python :: 3
Classifier: License :: OSI Approved :: GNU General Public License v3 (GPLv3)
Classifier: Operating System :: OS Independent
Requires-Python: >=3.7
